audioread/__init__.py
audioread/base.py
audioread/exceptions.py
audioread/ffdec.py
audioread/gstdec.py
audioread/macca.py
audioread/maddec.py
audioread/rawread.py
audioread-3.1.0a1.dist-info/METADATA
audioread-3.1.0a1.dist-info/WHEEL
audioread-3.1.0a1.dist-info/licenses/LICENSE
audioread-3.1.0a1.dist-info/RECORD
