Metadata-Version: 2.4
Name: audioread
Version: 3.1.0a1
Summary: Multi-library, cross-platform audio decoding.
License-Expression: MIT
License-File: LICENSE
Author: Adrian Sampson
Author-email: adrian@radbox.org
Requires-Python: >=3.9
Classifier: Topic :: Multimedia :: Sound/Audio :: Conversion
Classifier: Intended Audience :: Developers
Classifier: Programming Language :: Python :: 3
Classifier: Programming Language :: Python :: 3.9
Classifier: Programming Language :: Python :: 3.10
Classifier: Programming Language :: Python :: 3.11
Classifier: License :: OSI Approved :: MIT License
Provides-Extra: gi
Provides-Extra: mad
Provides-Extra: test
Requires-Dist: pygobject (>=3.54.2,<4.0.0) ; extra == "gi"
Requires-Dist: pymad[mad] (>=0.11.3,<0.12.0) ; extra == "mad"
Requires-Dist: pytest (>=8.4.2) ; extra == "test"
Requires-Dist: pytest-cov (>=7.0.0) ; extra == "test"
Project-URL: Bug Tracker, https://github.com/beetbox/audioread/issues
Project-URL: Homepage, https://github.com/beetbox/audioread
Project-URL: Repository, https://github.com/beetbox/audioread
